geoadmin/__init__.py
geoadmin/admin.py
geoadmin/options.py
geoadmin/version.py
geoadmin/static/geoadmin/geoadmin.css
geoadmin/static/geoadmin/geoadmin.js
geoadmin/templates/geoadmin/geoadmin_change_list.html
geoadmin/templates/geoadmin/geoadmin_view.html
django_geoadmin-0.0.2.dist-info/LICENSE
django_geoadmin-0.0.2.dist-info/METADATA
django_geoadmin-0.0.2.dist-info/WHEEL
django_geoadmin-0.0.2.dist-info/top_level.txt
django_geoadmin-0.0.2.dist-info/RECORD
